setup.cfg
setup.py
pyuia/__init__.py
pyuia/context.py
pyuia/exceptions.py
pyuia/pageobject.py
pyuia.egg-info/PKG-INFO
pyuia.egg-info/SOURCES.txt
pyuia.egg-info/dependency_links.txt
pyuia.egg-info/requires.txt
pyuia.egg-info/top_level.txt
pyuia/appium/__init__.py
pyuia/appium/context.py
pyuia/appium/pageobject.py
pyuia/appium/util.py
pyuia/robot/__init__.py
pyuia/robot/library.py
pyuia/robot/util.py
pyuia/selenium/__init__.py
pyuia/selenium/context.py
pyuia/selenium/pageobject.py