Metadata-Version: 1.1
Name: pyuia
Version: 0.3.3
Summary: PyUIA is a library aiming to facilitate the implementation of UI test automation with Python.
Home-page: https://github.com/imsardine/pyuia
Author: KKBOX SQA Team
Author-email: imsardine@gmail.com
License: MIT
Keywords: python,ui test automation,keyword-driven testing,page object pattern,appium,robot framework,mobile,android,ios
Platform: UNKNOWN
Classifier: Development Status :: 3 - Alpha
Classifier: Intended Audience :: Developers
Classifier: License :: OSI Approved :: MIT License
Classifier: Operating System :: OS Independent
Classifier: Programming Language :: Python
Classifier: Topic :: Software Development :: Quality Assurance
Classifier: Topic :: Software Development :: Testing
